robot_descriptions/__init__.py
robot_descriptions/__main__.py
robot_descriptions/_cache.py
robot_descriptions/_descriptions.py
robot_descriptions/_empty_description.py
robot_descriptions/_package_dirs.py
robot_descriptions/_repositories.py
robot_descriptions/a1_description.py
robot_descriptions/a1_mj_description.py
robot_descriptions/ability_hand_description.py
robot_descriptions/ability_hand_mj_description.py
robot_descriptions/adam_lite_mj_description.py
robot_descriptions/aliengo_description.py
robot_descriptions/aliengo_mj_description.py
robot_descriptions/allegro_hand_description.py
robot_descriptions/allegro_hand_mj_description.py
robot_descriptions/aloha_mj_description.py
robot_descriptions/anymal_b_description.py
robot_descriptions/anymal_b_mj_description.py
robot_descriptions/anymal_c_description.py
robot_descriptions/anymal_c_mj_description.py
robot_descriptions/anymal_d_description.py
robot_descriptions/apollo_mj_description.py
robot_descriptions/arx_l5_mj_description.py
robot_descriptions/atlas_drc_description.py
robot_descriptions/atlas_v4_description.py
robot_descriptions/b1_description.py
robot_descriptions/b2_description.py
robot_descriptions/bambot_description.py
robot_descriptions/barrett_hand_description.py
robot_descriptions/baxter_description.py
robot_descriptions/berkeley_humanoid_description.py
robot_descriptions/bolt_description.py
robot_descriptions/booster_t1_description.py
robot_descriptions/booster_t1_mj_description.py
robot_descriptions/cassie_description.py
robot_descriptions/cassie_mj_description.py
robot_descriptions/cf2_description.py
robot_descriptions/cf2_mj_description.py
robot_descriptions/double_pendulum_description.py
robot_descriptions/draco3_description.py
robot_descriptions/dynamixel_2r_mj_description.py
robot_descriptions/edo_description.py
robot_descriptions/elf2_description.py
robot_descriptions/elf2_mj_description.py
robot_descriptions/ergocub_description.py
robot_descriptions/eve_r3_description.py
robot_descriptions-1.21.0.dist-info/entry_points.txt
robot_descriptions-1.21.0.dist-info/licenses/LICENSE
robot_descriptions-1.21.0.dist-info/WHEEL
robot_descriptions-1.21.0.dist-info/METADATA
robot_descriptions-1.21.0.dist-info/RECORD
