Metadata-Version: 2.4
Name: robot_descriptions
Version: 1.21.0
Summary: Import open source robot description as Python modules.
Keywords: robot,description,urdf,mjcf
Author-email: Stéphane Caron <stephane.caron@normalesup.org>
Maintainer-email: Stéphane Caron <stephane.caron@normalesup.org>
Requires-Python: >=3.7
Classifier: Development Status :: 5 - Production/Stable
Classifier: Framework :: Robot Framework :: Library
Classifier: Intended Audience :: Developers
Classifier: Intended Audience :: Science/Research
Classifier: License :: OSI Approved :: Apache Software License
Classifier: Programming Language :: Python :: 3.9
Classifier: Programming Language :: Python :: 3.10
Classifier: Programming Language :: Python :: 3.11
Classifier: Programming Language :: Python :: 3.12
Classifier: Topic :: Scientific/Engineering
License-File: LICENSE
Requires-Dist: GitPython >=3.1.18
Requires-Dist: tqdm >=4.64.0
Requires-Dist: idyntree >= 8.0.0 ; extra == "opts"
Requires-Dist: mujoco >=3.2.0 ; extra == "opts"
Requires-Dist: pin >=2.6.10 ; extra == "opts"
Requires-Dist: pybullet >=3.2.6 ; extra == "opts"
Requires-Dist: robomeshcat >=1.0.4 ; extra == "opts"
Requires-Dist: yourdfpy >=0.0.56 ; extra == "opts"
Project-URL: Changelog, https://github.com/robot-descriptions/robot_descriptions.py/blob/main/CHANGELOG.md
Project-URL: Homepage, https://github.com/robot-descriptions
Project-URL: Source, https://github.com/robot-descriptions/robot_descriptions.py
Project-URL: Tracker, https://github.com/robot-descriptions/robot_descriptions.py/issues
Provides-Extra: opts
